{
  "status": "live",
  "generatedAt": "2026-07-18T12:46:38.969Z",
  "collection": {
    "startedAt": "2026-07-13T02:42:17.427Z",
    "latestAt": "2026-07-18T12:46:35.953Z",
    "totalRecords": 207449,
    "last24Hours": 153215,
    "realtimePrices": {
      "status": "healthy",
      "records": 17838,
      "last24Hours": 17838,
      "latestAt": "2026-07-18T12:46:35.953Z",
      "maximumSkewMs": 117467,
      "activeMarkets": 4,
      "assets": [
        "BTC",
        "ETH",
        "SOL",
        "XRP"
      ],
      "arbitrageViolations": 173,
      "targetCadenceSeconds": 5,
      "synchronizationVersion": "websocket-v6-near-term-discovery",
      "executionRecords": 11240,
      "executionLast24Hours": 11240,
      "executionLatestAt": "2026-07-18T12:46:35.953Z",
      "executionMaximumSkewMs": 12134,
      "executionSynchronizationVersion": "websocket-asset-v1"
    },
    "synchronizedPrices": {
      "records": 91606,
      "last24Hours": 91606,
      "latestAt": "2026-07-18T12:45:58.865Z",
      "maximumSkewMs": 19058,
      "targetCadenceMinutes": 1,
      "quality": {
        "status": "collecting",
        "records": 91606,
        "completeRecords": 91606,
        "windowRecords": 91606,
        "windowCompleteRecords": 91606,
        "totalRecords": 102780,
        "coverage": 0.8912823506518778,
        "durationHours": 1.6253480555555555,
        "startedAt": "2026-07-17T15:26:56.226Z",
        "continuousStartedAt": "2026-07-18T11:08:27.612Z",
        "latestAt": "2026-07-18T12:45:58.865Z",
        "medianSkewMs": 4003,
        "p95SkewMs": 4647,
        "medianSpread": 0.004000000000000004,
        "p95Spread": 0.03999999999999998,
        "medianAbsoluteBasisPct": 0.0002392373637541967,
        "p95AbsoluteBasisPct": 0.0006329957356077109,
        "maximumCaptureGapMs": 815799,
        "assets": [
          {
            "asset": "BTC",
            "records": 32289
          },
          {
            "asset": "ETH",
            "records": 23717
          },
          {
            "asset": "SOL",
            "records": 18018
          },
          {
            "asset": "XRP",
            "records": 17582
          }
        ],
        "passedGates": 5,
        "totalGates": 6,
        "gates": [
          {
            "id": "records",
            "label": "1,000件以上",
            "passed": true
          },
          {
            "id": "duration",
            "label": "48時間連続",
            "passed": false
          },
          {
            "id": "coverage",
            "label": "同期率50%以上",
            "passed": true
          },
          {
            "id": "timing",
            "label": "時刻ずれ95%点が60秒以内",
            "passed": true
          },
          {
            "id": "assets",
            "label": "4資産を網羅",
            "passed": true
          },
          {
            "id": "basis",
            "label": "価格差95%点が10bp以内",
            "passed": true
          }
        ]
      },
      "prospective": {
        "methodology": "prospective-1m-orderbook-holdout",
        "collectionStartedAt": "2026-07-17T15:26:56.226Z",
        "latestSnapshotAt": "2026-07-18T12:45:58.865Z",
        "generatedAt": "2026-07-18T12:46:38.969Z",
        "completedEvents": 0,
        "targetEvents": 50,
        "horizons": [
          {
            "horizonHours": 6,
            "scheduledMarkets": 10,
            "upcomingMarkets": 10,
            "observedMarkets": 0,
            "missedMarkets": 0,
            "awaitingExitMarkets": 0,
            "awaitingResolutionMarkets": 0,
            "completedMarkets": 0,
            "completedEvents": 0,
            "holdoutEvents": 0,
            "eventGroupingCoverage": 0,
            "observationCoverage": 0,
            "targetEvents": 50,
            "status": "collecting",
            "modelStatus": null,
            "trades": 0,
            "netReturnPct": null,
            "excessReturnPct": null
          },
          {
            "horizonHours": 12,
            "scheduledMarkets": 10,
            "upcomingMarkets": 10,
            "observedMarkets": 0,
            "missedMarkets": 0,
            "awaitingExitMarkets": 0,
            "awaitingResolutionMarkets": 0,
            "completedMarkets": 0,
            "completedEvents": 0,
            "holdoutEvents": 0,
            "eventGroupingCoverage": 0,
            "observationCoverage": 0,
            "targetEvents": 50,
            "status": "collecting",
            "modelStatus": null,
            "trades": 0,
            "netReturnPct": null,
            "excessReturnPct": null
          },
          {
            "horizonHours": 24,
            "scheduledMarkets": 10,
            "upcomingMarkets": 10,
            "observedMarkets": 0,
            "missedMarkets": 0,
            "awaitingExitMarkets": 0,
            "awaitingResolutionMarkets": 0,
            "completedMarkets": 0,
            "completedEvents": 0,
            "holdoutEvents": 0,
            "eventGroupingCoverage": 0,
            "observationCoverage": 0,
            "targetEvents": 50,
            "status": "collecting",
            "modelStatus": null,
            "trades": 0,
            "netReturnPct": null,
            "excessReturnPct": null
          },
          {
            "horizonHours": 48,
            "scheduledMarkets": 10,
            "upcomingMarkets": 10,
            "observedMarkets": 0,
            "missedMarkets": 0,
            "awaitingExitMarkets": 0,
            "awaitingResolutionMarkets": 0,
            "completedMarkets": 0,
            "completedEvents": 0,
            "holdoutEvents": 0,
            "eventGroupingCoverage": 0,
            "observationCoverage": 0,
            "targetEvents": 50,
            "status": "collecting",
            "modelStatus": null,
            "trades": 0,
            "netReturnPct": null,
            "excessReturnPct": null
          }
        ]
      }
    }
  },
  "tradeReadiness": {
    "objective": "Polymarketの予測をシグナルにしてHyperliquidで売買する",
    "currentStage": "shadow",
    "realTradingEnabled": false,
    "combinedPaperRunning": true,
    "hyperliquidOrderConnection": "connector_ready",
    "gates": [
      {
        "id": "data",
        "label": "同期データ品質",
        "status": "running"
      },
      {
        "id": "edge",
        "label": "優位性確認",
        "status": "blocked"
      },
      {
        "id": "shadow",
        "label": "シャドー検証",
        "status": "running"
      },
      {
        "id": "testnet",
        "label": "テストネット",
        "status": "attention"
      },
      {
        "id": "live",
        "label": "実取引",
        "status": "locked"
      }
    ]
  },
  "combinedShadow": {
    "status": "running",
    "startedAt": "2026-07-17T16:18:34.585Z",
    "updatedAt": "2026-07-18T12:45:54.740Z",
    "initialEquity": 40000,
    "equity": 39998.870507218104,
    "returnPct": 0,
    "cash": 39999.775,
    "realizedPnl": 0,
    "openPositions": [
      {
        "asset": "BTC",
        "side": "SHORT",
        "quantity": 0.007800837954467829,
        "entryPrice": 64095.6783,
        "markPrice": 64170.5,
        "signalZ": -0.6255913555132823,
        "polymarketSide": "SHORT",
        "entryTrendZ6h": 0.448099556973332,
        "entryFunding24h": 0.0003,
        "horizonHours": 48,
        "priceBasisPct": -0.0004131909253917154,
        "openedAt": "2026-07-18T12:01:43.058Z",
        "exitAt": "2026-07-20T16:00:00.000Z"
      }
    ],
    "trades": 0,
    "wins": 0,
    "winRate": null,
    "maxDrawdownPct": 0.0001184735854640167,
    "riskStatus": "NORMAL",
    "emergencyStopped": false,
    "experimentKey": "forward-v2-6-12-24-48",
    "experimentLabel": "6・12・24・48時間の独立フォワード検証 v2",
    "forwardOnly": true,
    "minimumSignalZ": 0.25,
    "minimumFunding24h": 0.0003,
    "signalRule": "polymarket-funding-consensus",
    "modelVersion": "Forward Experiment v2 2026-07-18 / no backfill",
    "forwardEvaluation": {
      "status": "collecting",
      "trades": 0,
      "independentEvents": 0,
      "wins": 0,
      "winRate": null,
      "controlTrades": 0,
      "comparableEvents": 0,
      "minimumTrades": 50,
      "minimumIndependentEvents": 50,
      "minimumComparableEvents": 50,
      "progressPct": 0,
      "comparisonStartedAt": "2026-07-17T16:18:34.611Z",
      "netReturnPct": null,
      "benchmarkReturnPct": null,
      "benchmarkLabel": null,
      "excessReturnPct": null,
      "excessConfidenceInterval95": null,
      "deflatedSharpeProbability": null,
      "randomBenchmarkTrials": 200,
      "maxDrawdownPct": 0,
      "passedGates": 0,
      "totalGates": 8,
      "gates": [
        {
          "id": "trades",
          "label": "50独立イベント以上",
          "passed": false
        },
        {
          "id": "control",
          "label": "同期間比較50件以上",
          "passed": false
        },
        {
          "id": "net-positive",
          "label": "コスト控除後プラス",
          "passed": false
        },
        {
          "id": "benchmark",
          "label": "最良の単純戦略を上回る",
          "passed": false
        },
        {
          "id": "significance",
          "label": "平均との差の95%下限がプラス",
          "passed": false
        },
        {
          "id": "selection-bias",
          "label": "固定実験の確信度95%以上",
          "passed": false
        },
        {
          "id": "drawdown",
          "label": "最大下落5%以内",
          "passed": false
        },
        {
          "id": "settlement",
          "label": "判定価格の整合性を確認",
          "passed": false
        }
      ],
      "benchmarks": {
        "polymarketOnlyReturnPct": null,
        "alwaysLongReturnPct": null,
        "alwaysShortReturnPct": null,
        "randomMedianReturnPct": null
      },
      "attribution": {
        "byAsset": []
      },
      "activeHorizonHours": 24,
      "totalTrades": 0,
      "totalIndependentEvents": 0,
      "totalMinimumTrades": 200,
      "totalMinimumIndependentEvents": 200,
      "horizons": [
        {
          "horizonHours": 6,
          "status": "collecting",
          "trades": 0,
          "independentEvents": 0,
          "minimumTrades": 50,
          "minimumIndependentEvents": 50,
          "progressPct": 0,
          "netReturnPct": null,
          "excessReturnPct": null,
          "maxDrawdownPct": 0,
          "passedGates": 0,
          "totalGates": 8,
          "horizonEligibleMarkets": 0,
          "priceReadyEvents": 0,
          "latestAction": "NO_SIGNAL",
          "latestReason": "次の6時間観測は7/20 17:00です",
          "nextWindowAt": "2026-07-20T08:00:00.000Z"
        },
        {
          "horizonHours": 12,
          "status": "collecting",
          "trades": 0,
          "independentEvents": 0,
          "minimumTrades": 50,
          "minimumIndependentEvents": 50,
          "progressPct": 0,
          "netReturnPct": null,
          "excessReturnPct": null,
          "maxDrawdownPct": 0,
          "passedGates": 0,
          "totalGates": 8,
          "horizonEligibleMarkets": 0,
          "priceReadyEvents": 0,
          "latestAction": "NO_SIGNAL",
          "latestReason": "次の12時間観測は7/20 11:00です",
          "nextWindowAt": "2026-07-20T02:00:00.000Z"
        },
        {
          "horizonHours": 24,
          "status": "collecting",
          "trades": 0,
          "independentEvents": 0,
          "minimumTrades": 50,
          "minimumIndependentEvents": 50,
          "progressPct": 0,
          "netReturnPct": null,
          "excessReturnPct": null,
          "maxDrawdownPct": 0,
          "passedGates": 0,
          "totalGates": 8,
          "horizonEligibleMarkets": 0,
          "priceReadyEvents": 0,
          "latestAction": "NO_SIGNAL",
          "latestReason": "次の24時間観測は7/19 22:00です",
          "nextWindowAt": "2026-07-19T13:00:00.000Z"
        },
        {
          "horizonHours": 48,
          "status": "collecting",
          "trades": 0,
          "independentEvents": 0,
          "minimumTrades": 50,
          "minimumIndependentEvents": 50,
          "progressPct": 0,
          "netReturnPct": null,
          "excessReturnPct": null,
          "maxDrawdownPct": 0.0001184735854640167,
          "passedGates": 0,
          "totalGates": 8,
          "horizonEligibleMarkets": 11,
          "priceReadyEvents": 1,
          "latestAction": "SKIP",
          "latestReason": "同じ予測テーマと時間軸はすでに検証済み",
          "nextWindowAt": null
        }
      ]
    },
    "shortTermDirection": {
      "status": "collecting",
      "running": true,
      "startedAt": "2026-07-18T06:35:12.058Z",
      "updatedAt": "2026-07-18T12:45:54.737Z",
      "trades": 38,
      "controlTrades": 41,
      "minimumTrades": 50,
      "progressPct": 0.76,
      "netReturnPct": -0.0021261409038385993,
      "excessReturnPct": -0.0003376535204604829,
      "confidenceLowerPct": -0.0011446793945172219,
      "maxDrawdownPct": 0.0021313518770970405,
      "passedGates": 0,
      "totalGates": 9,
      "openPositions": 0,
      "scannedMarkets": 37,
      "fifteenMinuteMarkets": 8,
      "decisionWindowMarkets": 0,
      "priceReadyMarkets": 0,
      "thresholdSignals": 38,
      "opened": 38,
      "latestAction": "NO_SIGNAL",
      "latestReason": "次回は7/18 21:47",
      "nextDecisionAt": "2026-07-18T12:47:00.000Z",
      "observedAt": "2026-07-18T12:45:54.737Z",
      "specificationHash": "655dac2ae6bf6768",
      "executionAudit": {
        "status": "collecting",
        "readinessStatus": "collecting",
        "priceSources": {
          "entry": "Polymarket CLOB 5秒板",
          "exit": "Hyperliquid L2 独立5秒板",
          "settlement": "Chainlink 独立5秒価格"
        },
        "collectionStartedAt": "2026-07-18T06:35:18.248Z",
        "minimumAuditedPositions": 50,
        "minimumIndependentEvents": 50,
        "eligiblePositions": 38,
        "auditedPositions": 33,
        "coverage": 0.868421052631579,
        "verifiedPositions": 31,
        "verifiedIndependentEvents": 17,
        "verifiedCoverage": 0.8157894736842105,
        "resolvedPredictions": 36,
        "predictionAccuracy": 0.8055555555555556,
        "polymarketAuditedPositions": 35,
        "polymarketNetReturnPct": 0.09944090441718101,
        "hyperliquidNetReturnPct": -0.0013808709466604926,
        "storedNetReturnPct": -0.001285584601270781,
        "portfolioNetReturnPct": -0.0021261409038385993,
        "storedPortfolioReturnPct": -0.0019780231562918603,
        "meanTradeReturnConfidenceInterval95": [
          -0.0017224840012585586,
          -0.0009906652245077901
        ],
        "benchmarkReturnPct": -0.0017884873833781164,
        "benchmarkLabel": "常時ショート",
        "excessReturnPct": -0.0003376535204604829,
        "excessConfidenceInterval95": [
          -0.0011446793945172219,
          0.000472206749124492
        ],
        "deflatedSharpeProbability": 0.021130999350088386,
        "strategyTrials": 11,
        "randomBenchmarkTrials": 200,
        "maxDrawdownPct": 0.0021313518770970405,
        "attribution": {
          "byAsset": [
            {
              "asset": "ETH",
              "trades": 14,
              "wins": 1,
              "netPnl": -8.926267182855979,
              "returnContributionPct": -0.0008926267182855979
            },
            {
              "asset": "SOL",
              "trades": 10,
              "wins": 0,
              "netPnl": -9.310895053690398,
              "returnContributionPct": -0.0009310895053690399
            },
            {
              "asset": "XRP",
              "trades": 7,
              "wins": 0,
              "netPnl": -3.0242468018396185,
              "returnContributionPct": -0.00030242468018396186
            }
          ],
          "bySide": [
            {
              "side": "LONG",
              "trades": 17,
              "wins": 0,
              "netPnl": -13.797470305782854,
              "returnContributionPct": -0.0013797470305782853
            },
            {
              "side": "SHORT",
              "trades": 14,
              "wins": 1,
              "netPnl": -7.463938732603143,
              "returnContributionPct": -0.0007463938732603144
            }
          ]
        },
        "controlComparablePositions": 34,
        "comparableEvents": 34,
        "comparableIndependentEvents": 18,
        "controlCoverage": 1,
        "benchmarks": {
          "polymarketOnlyReturnPct": -0.00225628687384911,
          "alwaysLongReturnPct": -0.0027982219705839457,
          "alwaysShortReturnPct": -0.0017884873833781164,
          "randomMedianReturnPct": -0.0022671488761450034
        },
        "passedReadinessGates": 0,
        "totalReadinessGates": 9,
        "readinessGates": [
          {
            "id": "trades",
            "label": "50件の独立時間枠を完全監査",
            "passed": false
          },
          {
            "id": "execution",
            "label": "実板・時刻・決着の監査率95%以上",
            "passed": false
          },
          {
            "id": "control",
            "label": "同時対照の再現率95%以上",
            "passed": false
          },
          {
            "id": "net-positive",
            "label": "全コスト控除後プラス",
            "passed": false
          },
          {
            "id": "benchmark",
            "label": "最良の単純戦略を上回る",
            "passed": false
          },
          {
            "id": "significance",
            "label": "対照との差の95%下限がプラス",
            "passed": false
          },
          {
            "id": "selection-bias",
            "label": "試行補正後の確信度95%以上",
            "passed": false
          },
          {
            "id": "drawdown",
            "label": "最大下落5%以内",
            "passed": false
          },
          {
            "id": "settlement",
            "label": "Chainlink方向とPolymarket正式決着が一致",
            "passed": false
          }
        ],
        "settlementResolutionStatus": "attention",
        "returnDifferencePct": -0.0000952863453897116,
        "medianTimingErrorMs": 769,
        "maximumTimingErrorMs": 6280,
        "medianPolymarketQuoteAgeMs": 61,
        "maximumPolymarketQuoteAgeMs": 314,
        "medianCloseDelayMs": 44740,
        "maximumCloseDelayMs": 72143,
        "allowedTimingErrorMs": 15000,
        "allowedPolymarketQuoteAgeMs": 120000,
        "missingEntry": 1,
        "missingExit": 4,
        "missingResolution": 2
      },
      "settlementResolution": {
        "status": "attention",
        "source": "CHAINLINK",
        "rule": "終了価格が開始価格以上ならUp",
        "targetMarkets": 50,
        "resolvedObservedMarkets": 92,
        "completeMarkets": 76,
        "missingBoundaryMarkets": 16,
        "matchedMarkets": 76,
        "mismatchedMarkets": 0,
        "coverage": 0.8260869565217391,
        "matchRate": 1,
        "medianBoundaryErrorMs": 1000,
        "maximumBoundaryErrorMs": 3000,
        "allowedBoundaryErrorMs": 60000,
        "byAsset": [
          {
            "asset": "BTC",
            "completeMarkets": 19,
            "matchedMarkets": 19,
            "mismatchedMarkets": 0
          },
          {
            "asset": "ETH",
            "completeMarkets": 19,
            "matchedMarkets": 19,
            "mismatchedMarkets": 0
          },
          {
            "asset": "SOL",
            "completeMarkets": 19,
            "matchedMarkets": 19,
            "mismatchedMarkets": 0
          },
          {
            "asset": "XRP",
            "completeMarkets": 19,
            "matchedMarkets": 19,
            "mismatchedMarkets": 0
          }
        ],
        "passedGates": 3,
        "totalGates": 4,
        "gates": [
          {
            "id": "samples",
            "label": "公式決着50市場以上",
            "passed": true
          },
          {
            "id": "coverage",
            "label": "開始・終了価格の取得率95%以上",
            "passed": false
          },
          {
            "id": "agreement",
            "label": "Chainlink方向と正式決着の不一致0件",
            "passed": true
          },
          {
            "id": "timing",
            "label": "境界価格の時刻誤差60秒以内",
            "passed": true
          }
        ]
      },
      "research": {
        "generatedAt": "2026-07-18T10:06:59.981Z",
        "marketDuration": "15m",
        "executionMode": "taker",
        "lookbackHours": 72,
        "completeMarkets": 1147,
        "walkForwardFolds": 4,
        "minimumProfitableFolds": 3,
        "acceptedCandidates": 0,
        "totalCandidates": 4,
        "currentCandidateId": "baseline",
        "diagnosis": {
          "verdict": "cost_barrier",
          "trades": 278,
          "binaryOutcomeAccuracy": 0.7158273381294964,
          "afterCostWinRate": 0.1079136690647482,
          "estimatedBeforeCostWinRate": 0.49280575539568344,
          "averageNetReturnPct": -0.0012983885068514377,
          "estimatedBeforeCostAverageReturnPct": 0.0000016114931485622337,
          "assumedRoundTripCostPct": 0.0013,
          "slices": {
            "byAsset": [
              {
                "key": "BTC",
                "label": "BTC",
                "trades": 66,
                "profitableTrades": 8,
                "afterCostWinRate": 0.12121212121212122,
                "averageReturnPct": -0.0012156002423584732,
                "netReturnPct": -0.004011480799782962
              },
              {
                "key": "ETH",
                "label": "ETH",
                "trades": 62,
                "profitableTrades": 7,
                "afterCostWinRate": 0.11290322580645161,
                "averageReturnPct": -0.001371396330236121,
                "netReturnPct": -0.004251328623731975
              },
              {
                "key": "SOL",
                "label": "SOL",
                "trades": 68,
                "profitableTrades": 7,
                "afterCostWinRate": 0.10294117647058823,
                "averageReturnPct": -0.001356840610203144,
                "netReturnPct": -0.00461325807469069
              },
              {
                "key": "XRP",
                "label": "XRP",
                "trades": 82,
                "profitableTrades": 8,
                "afterCostWinRate": 0.0975609756097561,
                "averageReturnPct": -0.0012613494504949644,
                "netReturnPct": -0.0051715327470293546
              }
            ],
            "bySide": [
              {
                "key": "LONG",
                "label": "LONG",
                "trades": 137,
                "profitableTrades": 15,
                "afterCostWinRate": 0.10948905109489052,
                "averageReturnPct": -0.0011919023845209534,
                "netReturnPct": -0.00816453133396853
              },
              {
                "key": "SHORT",
                "label": "SHORT",
                "trades": 141,
                "profitableTrades": 15,
                "afterCostWinRate": 0.10638297872340426,
                "averageReturnPct": -0.0014018537462789304,
                "netReturnPct": -0.00988306891126646
              }
            ],
            "byProbability": [
              {
                "key": "58-60",
                "label": "0.58-0.60",
                "trades": 30,
                "profitableTrades": 4,
                "afterCostWinRate": 0.13333333333333333,
                "averageReturnPct": -0.0011689080287081606,
                "netReturnPct": -0.001753362043062241
              },
              {
                "key": "60-65",
                "label": "0.60-0.65",
                "trades": 66,
                "profitableTrades": 7,
                "afterCostWinRate": 0.10606060606060606,
                "averageReturnPct": -0.0013142756513216454,
                "netReturnPct": -0.0043371096493614305
              },
              {
                "key": "65-70",
                "label": "0.65-0.70",
                "trades": 57,
                "profitableTrades": 3,
                "afterCostWinRate": 0.05263157894736842,
                "averageReturnPct": -0.0019124379133714192,
                "netReturnPct": -0.0054504480531085454
              },
              {
                "key": "70-80",
                "label": "0.70-0.80",
                "trades": 90,
                "profitableTrades": 14,
                "afterCostWinRate": 0.15555555555555556,
                "averageReturnPct": -0.0009719112631303454,
                "netReturnPct": -0.004373600684086555
              },
              {
                "key": "80-plus",
                "label": "0.80+",
                "trades": 35,
                "profitableTrades": 2,
                "afterCostWinRate": 0.05714285714285714,
                "averageReturnPct": -0.0012189027517806922,
                "netReturnPct": -0.0021330798156162113
              }
            ],
            "byTrendStrength": [
              {
                "key": "015-030",
                "label": "0.15-0.30",
                "trades": 23,
                "profitableTrades": 3,
                "afterCostWinRate": 0.13043478260869565,
                "averageReturnPct": -0.0013937879878500575,
                "netReturnPct": -0.0016028561860275661
              },
              {
                "key": "030-060",
                "label": "0.30-0.60",
                "trades": 68,
                "profitableTrades": 6,
                "afterCostWinRate": 0.08823529411764706,
                "averageReturnPct": -0.0014518734860667192,
                "netReturnPct": -0.004936369852626846
              },
              {
                "key": "060-100",
                "label": "0.60-1.00",
                "trades": 54,
                "profitableTrades": 8,
                "afterCostWinRate": 0.14814814814814814,
                "averageReturnPct": -0.001358480380983025,
                "netReturnPct": -0.003667897028654168
              },
              {
                "key": "100-200",
                "label": "1.00-2.00",
                "trades": 96,
                "profitableTrades": 10,
                "afterCostWinRate": 0.10416666666666667,
                "averageReturnPct": -0.0011545318683698564,
                "netReturnPct": -0.005541752968175311
              },
              {
                "key": "200-plus",
                "label": "2.00+",
                "trades": 37,
                "profitableTrades": 3,
                "afterCostWinRate": 0.08108108108108109,
                "averageReturnPct": -0.001242553626892482,
                "netReturnPct": -0.0022987242097510913
              }
            ],
            "byJstSession": [
              {
                "key": "00-05",
                "label": "00-05 JST",
                "trades": 56,
                "profitableTrades": 10,
                "afterCostWinRate": 0.17857142857142858,
                "averageReturnPct": -0.0010950657105623797,
                "netReturnPct": -0.003066183989574663
              },
              {
                "key": "06-11",
                "label": "06-11 JST",
                "trades": 62,
                "profitableTrades": 2,
                "afterCostWinRate": 0.03225806451612903,
                "averageReturnPct": -0.001299382990347834,
                "netReturnPct": -0.004028087270078286
              },
              {
                "key": "12-17",
                "label": "12-17 JST",
                "trades": 91,
                "profitableTrades": 5,
                "afterCostWinRate": 0.054945054945054944,
                "averageReturnPct": -0.0014080549225627987,
                "netReturnPct": -0.006406649897660734
              },
              {
                "key": "18-23",
                "label": "18-23 JST",
                "trades": 69,
                "profitableTrades": 13,
                "afterCostWinRate": 0.18840579710144928,
                "averageReturnPct": -0.0013178779964989268,
                "netReturnPct": -0.0045466790879212975
              }
            ]
          }
        },
        "sensitivity": {
          "purpose": "diagnostic_only",
          "selectionPolicy": "fixed_grid_not_used_for_promotion",
          "testedVariants": 9,
          "calibrationPositiveVariants": 0,
          "holdoutPositiveVariants": 0,
          "variants": [
            {
              "id": "p58-t15",
              "minimumProbability": 0.58,
              "minimumTrendZ": 0.15,
              "calibration": {
                "trades": 436,
                "netReturnPct": -0.02125224694901538,
                "averageReturnPct": -0.000974873713257587
              },
              "holdout": {
                "trades": 278,
                "netReturnPct": -0.01804760024523498,
                "averageReturnPct": -0.0012983885068514377
              }
            },
            {
              "id": "p58-t60",
              "minimumProbability": 0.58,
              "minimumTrendZ": 0.6,
              "calibration": {
                "trades": 326,
                "netReturnPct": -0.015440687904758645,
                "averageReturnPct": -0.0009472814665496107
              },
              "holdout": {
                "trades": 202,
                "netReturnPct": -0.012558604057247496,
                "averageReturnPct": -0.0012434261442819312
              }
            },
            {
              "id": "p58-t100",
              "minimumProbability": 0.58,
              "minimumTrendZ": 1,
              "calibration": {
                "trades": 223,
                "netReturnPct": -0.011250960673812552,
                "averageReturnPct": -0.0010090547689517982
              },
              "holdout": {
                "trades": 152,
                "netReturnPct": -0.009450039264650573,
                "averageReturnPct": -0.0012434262190329705
              }
            },
            {
              "id": "p65-t15",
              "minimumProbability": 0.65,
              "minimumTrendZ": 0.15,
              "calibration": {
                "trades": 332,
                "netReturnPct": -0.014891095839198589,
                "averageReturnPct": -0.0008970539662167829
              },
              "holdout": {
                "trades": 209,
                "netReturnPct": -0.013920447206142522,
                "averageReturnPct": -0.0013321002111141168
              }
            },
            {
              "id": "p65-t60",
              "minimumProbability": 0.65,
              "minimumTrendZ": 0.6,
              "calibration": {
                "trades": 272,
                "netReturnPct": -0.012745887955490396,
                "averageReturnPct": -0.0009371976437860589
              },
              "holdout": {
                "trades": 167,
                "netReturnPct": -0.010428871233643878,
                "averageReturnPct": -0.0012489666148076512
              }
            },
            {
              "id": "p65-t100",
              "minimumProbability": 0.65,
              "minimumTrendZ": 1,
              "calibration": {
                "trades": 206,
                "netReturnPct": -0.010566493479899585,
                "averageReturnPct": -0.001025873153388309
              },
              "holdout": {
                "trades": 138,
                "netReturnPct": -0.008232189439977488,
                "averageReturnPct": -0.0011930709333300706
              }
            },
            {
              "id": "p70-t15",
              "minimumProbability": 0.7,
              "minimumTrendZ": 0.15,
              "calibration": {
                "trades": 258,
                "netReturnPct": -0.012215949394748685,
                "averageReturnPct": -0.0009469728212983484
              },
              "holdout": {
                "trades": 162,
                "netReturnPct": -0.009282466287267633,
                "averageReturnPct": -0.001145983492255264
              }
            },
            {
              "id": "p70-t60",
              "minimumProbability": 0.7,
              "minimumTrendZ": 0.6,
              "calibration": {
                "trades": 228,
                "netReturnPct": -0.012036193919962638,
                "averageReturnPct": -0.0010558064842072499
              },
              "holdout": {
                "trades": 142,
                "netReturnPct": -0.007952638361284507,
                "averageReturnPct": -0.0011200899100400716
              }
            },
            {
              "id": "p70-t100",
              "minimumProbability": 0.7,
              "minimumTrendZ": 1,
              "calibration": {
                "trades": 184,
                "netReturnPct": -0.009595741962069044,
                "averageReturnPct": -0.001043015430659679
              },
              "holdout": {
                "trades": 120,
                "netReturnPct": -0.0068476153261936975,
                "averageReturnPct": -0.0011412692210322824
              }
            }
          ]
        },
        "history": [
          {
            "generatedAt": "2026-07-18T10:06:59.981Z",
            "marketDuration": "15m",
            "lookbackHours": 72,
            "executionMode": "taker",
            "completeMarkets": 1147,
            "status": "rejected",
            "trades": 278,
            "netReturnPct": -0.018047600245234982,
            "averageReturnPct": -0.0012983885068514377,
            "confidenceLowerPct": -0.00019011321805344604,
            "excessReturnPct": 0.0012193636590087013,
            "maxDrawdownPct": 0.018257245879972465,
            "profitableFolds": 0,
            "totalFolds": 4,
            "passedGates": 2,
            "totalGates": 7
          }
        ],
        "candidates": [
          {
            "id": "baseline",
            "label": "現行15分モデル",
            "status": "rejected",
            "trades": 278,
            "netReturnPct": -0.018047600245234982,
            "averageReturnPct": -0.0012983885068514377,
            "confidenceLowerPct": -0.00019011321805344604,
            "excessReturnPct": 0.0012193636590087013,
            "maxDrawdownPct": 0.018257245879972465,
            "profitableFolds": 0,
            "totalFolds": 4,
            "passedGates": 2,
            "totalGates": 7
          },
          {
            "id": "implied",
            "label": "暗黙終値",
            "status": "insufficient",
            "trades": 27,
            "netReturnPct": -0.003100707517557926,
            "averageReturnPct": -0.002296820383376242,
            "confidenceLowerPct": -0.00046764682497435473,
            "excessReturnPct": -0.0021224571106587143,
            "maxDrawdownPct": 0.0031326810150781315,
            "profitableFolds": 0,
            "totalFolds": 4,
            "passedGates": 0,
            "totalGates": 7
          },
          {
            "id": "leadLag",
            "label": "確率変化",
            "status": "rejected",
            "trades": 204,
            "netReturnPct": -0.012574952726816023,
            "averageReturnPct": -0.0012328385026290228,
            "confidenceLowerPct": -0.00016952288312540347,
            "excessReturnPct": -0.00011832907045577748,
            "maxDrawdownPct": 0.012498722422852104,
            "profitableFolds": 0,
            "totalFolds": 4,
            "passedGates": 2,
            "totalGates": 7
          },
          {
            "id": "crossSectional",
            "label": "資産間比較",
            "status": "insufficient",
            "trades": 0,
            "netReturnPct": 0,
            "averageReturnPct": null,
            "confidenceLowerPct": null,
            "excessReturnPct": 0,
            "maxDrawdownPct": 0,
            "profitableFolds": 0,
            "totalFolds": 4,
            "passedGates": 0,
            "totalGates": 7
          }
        ]
      },
      "realtimeResearch": {
        "generatedAt": "2026-07-18T12:22:18.850Z",
        "status": "insufficient",
        "promotionAllowed": false,
        "completeMarkets": 92,
        "replayableMarkets": 43,
        "independentWindows": 16,
        "minimumHoldoutWindows": 20,
        "selectedTrades": 166,
        "strategyTrials": 9,
        "calibrationPositiveVariants": 2,
        "holdoutPositiveVariants": 7,
        "calibrationBenchmarkBeatingVariants": 0,
        "holdoutBenchmarkBeatingVariants": 0,
        "selectedCandidate": {
          "id": "market_direction-30s",
          "strategy": "market_direction",
          "entryOffsetSeconds": 30,
          "calibration": {
            "independentWindows": 5,
            "trades": 8,
            "correctTrades": 5,
            "directionAccuracy": 0.625,
            "equalWeightWinRate": 0.625,
            "equalWeightAverageReturnPct": -0.010920314548936355,
            "equalWeightNetReturnPct": -0.004368125819574534,
            "equalWeightConfidenceInterval95": [
              -0.014328531425698713,
              0.012581281097868897
            ],
            "deflatedSharpeProbability": null,
            "hyperliquidAverageReturnPct": -0.001384120919318826,
            "hyperliquidNetReturnPct": -0.0005536483677275304,
            "polymarketAverageReturnPct": -0.020456508178553837,
            "polymarketNetReturnPct": -0.008182603271421549,
            "maximumDrawdownPct": 0.046594477595678696,
            "bestBenchmarkId": "random_median",
            "bestBenchmarkNetReturnPct": 0.014484510908034182,
            "excessReturnPct": -0.018852636727608715,
            "excessAverageReturnPct": -0.00377052734552174,
            "excessConfidenceInterval95": [
              -0.0333213746949547,
              0.025780320003911218
            ],
            "excessDeflatedSharpeProbability": null,
            "benchmarks": {
              "polymarketOnlyNetReturnPct": -0.008182603271421549,
              "hyperliquidOnlyNetReturnPct": -0.0005536483677275304,
              "alwaysLongNetReturnPct": -0.004368125819574534,
              "alwaysShortNetReturnPct": 0.008859893231243157,
              "randomMedianNetReturnPct": 0.014484510908034182
            }
          },
          "holdout": {
            "independentWindows": 3,
            "trades": 4,
            "correctTrades": 4,
            "directionAccuracy": 1,
            "equalWeightWinRate": 1,
            "equalWeightAverageReturnPct": 0.28629471452570654,
            "equalWeightNetReturnPct": 0.05725894290514131,
            "equalWeightConfidenceInterval95": [
              0.0024454913133410833,
              0.035727137290086454
            ],
            "deflatedSharpeProbability": null,
            "hyperliquidAverageReturnPct": -0.0004872671597473349,
            "hyperliquidNetReturnPct": -0.00009745343194946699,
            "polymarketAverageReturnPct": 0.5730766962111604,
            "polymarketNetReturnPct": 0.11461533924223208,
            "maximumDrawdownPct": 0,
            "bestBenchmarkId": "polymarket_only",
            "bestBenchmarkNetReturnPct": 0.11461533924223208,
            "excessReturnPct": -0.05735639633709077,
            "excessAverageReturnPct": -0.01911879877903026,
            "excessConfidenceInterval95": [
              -0.03579184560358088,
              -0.002445751954479637
            ],
            "excessDeflatedSharpeProbability": null,
            "benchmarks": {
              "polymarketOnlyNetReturnPct": 0.11461533924223208,
              "hyperliquidOnlyNetReturnPct": -0.00009745343194946699,
              "alwaysLongNetReturnPct": 0.05725894290514131,
              "alwaysShortNetReturnPct": -0.10022196270803795,
              "randomMedianNetReturnPct": -0.02155501370793418
            }
          },
          "profitableFolds": 2,
          "benchmarkBeatingFolds": 0,
          "totalFolds": 4
        },
        "reproducibility": {
          "runId": "2026-07-18T12-22-18.850Z",
          "codeRevision": "4b0342724986967ab37281bd4df78dd4e2797724",
          "specificationSha256": "6565d7e509fde502309a624e776434297855a1d488217935607c871661f59ce0",
          "datasetSha256": "90527b250b2cd6a5e8f398e9b8439a09c4ddfc9b471d79be89805cfa2135c58a",
          "hashAlgorithm": "sha256",
          "tradeRows": 166,
          "tradesCsvSha256": "480c824e99ac7b697e42bd16ca0ec5f565387f4986b1a1be751b4a7752748206"
        },
        "history": [
          {
            "runId": "2026-07-18T12-22-18.850Z",
            "generatedAt": "2026-07-18T12:22:18.850Z",
            "status": "insufficient",
            "selectedCandidateId": "market_direction-30s",
            "completeMarkets": 92,
            "replayableMarkets": 43,
            "independentWindows": 16,
            "holdoutWindows": 3,
            "holdoutTrades": 4,
            "holdoutEqualWeightNetReturnPct": 0.05725894290514131,
            "holdoutHyperliquidNetReturnPct": -0.00009745343194946699,
            "holdoutPolymarketNetReturnPct": 0.11461533924223208,
            "holdoutBestBenchmarkId": "polymarket_only",
            "holdoutBestBenchmarkNetReturnPct": 0.11461533924223208,
            "holdoutExcessReturnPct": -0.05735639633709077,
            "holdoutExcessConfidenceLowerPct": -0.03579184560358088,
            "profitableFolds": 2,
            "benchmarkBeatingFolds": 0,
            "totalFolds": 4,
            "codeRevision": "4b0342724986967ab37281bd4df78dd4e2797724",
            "datasetSha256": "90527b250b2cd6a5e8f398e9b8439a09c4ddfc9b471d79be89805cfa2135c58a",
            "specificationSha256": "6565d7e509fde502309a624e776434297855a1d488217935607c871661f59ce0"
          },
          {
            "runId": "2026-07-18T11-40-08.211Z",
            "generatedAt": "2026-07-18T11:40:08.211Z",
            "status": "insufficient",
            "selectedCandidateId": "market_direction-120s",
            "completeMarkets": 80,
            "replayableMarkets": 35,
            "independentWindows": 13,
            "holdoutWindows": 6,
            "holdoutTrades": 8,
            "holdoutEqualWeightNetReturnPct": 0.09146543476303749,
            "holdoutHyperliquidNetReturnPct": -0.00029937169292407976,
            "holdoutPolymarketNetReturnPct": 0.18323024121899908,
            "holdoutBestBenchmarkId": "polymarket_only",
            "holdoutBestBenchmarkNetReturnPct": 0.18323024121899908,
            "holdoutExcessReturnPct": -0.09176480645596159,
            "holdoutExcessConfidenceLowerPct": -0.018283113773176936,
            "profitableFolds": 2,
            "benchmarkBeatingFolds": 0,
            "totalFolds": 4,
            "codeRevision": "e64f2afe84373fccaa4a43449fb99aa69c0cda9c",
            "datasetSha256": "56b56e4f3f1b1720c97445a89632d124fe701efecbfa2f5c5a7503e9c03343df",
            "specificationSha256": "fbe61f9c498a26d911fbe3178cf3c8f8c5d16d00a908626954a269ccb2ac8497"
          },
          {
            "runId": "2026-07-18T11-09-31.145Z",
            "generatedAt": "2026-07-18T11:09:31.145Z",
            "status": "insufficient",
            "selectedCandidateId": "market_direction-120s",
            "completeMarkets": 72,
            "replayableMarkets": 34,
            "independentWindows": 12,
            "holdoutWindows": 5,
            "holdoutTrades": 7,
            "holdoutEqualWeightNetReturnPct": 0.0828636990639195,
            "holdoutHyperliquidNetReturnPct": -0.0002802003539616162,
            "holdoutPolymarketNetReturnPct": 0.16600759848180063,
            "profitableFolds": 2,
            "totalFolds": 4,
            "codeRevision": "39258658687a6443df28e64f80a37f4890d762f0",
            "datasetSha256": "8a4424593a448c7cb6e898d815c332479ce5b524f0f1d361d217aa71a393f2d2",
            "specificationSha256": "0fbc77629f342025cd17eacc5e5ce1d2f6a4587f593b2b018d6c161cfca890f1"
          }
        ]
      },
      "realTradingEnabled": false
    },
    "settlementBasis": {
      "status": "collecting",
      "samples": 0,
      "medianAbsolutePct": null,
      "maximumAbsolutePct": null,
      "medianReferenceCaptureLagSeconds": null
    },
    "funnel": {
      "scans": 284,
      "scannedMarkets": 83,
      "structuredMarkets": 11,
      "horizonEligibleMarkets": 11,
      "groupedEvents": 1,
      "priceReadyEvents": 1,
      "thresholdSignals": 13,
      "opened": 1,
      "closed": 0
    },
    "latestDecision": {
      "action": "NO_SIGNAL",
      "reason": "次の24時間観測は7/19 22:00です",
      "asset": null,
      "signalZ": null,
      "spotPrice": null,
      "targetPrice": null,
      "polymarketSide": null,
      "strategySide": null,
      "trendZ6h": null,
      "hyperliquidFunding24h": null,
      "horizonHours": 24,
      "marketBestBid": null,
      "marketBestAsk": null,
      "marketSpread": null,
      "polymarketReferencePrice": null,
      "referenceSource": null,
      "priceBasisPct": null,
      "ladderViolations": null,
      "nextWindowAt": "2026-07-19T13:00:00.000Z",
      "observedAt": "2026-07-18T12:45:54.740Z"
    },
    "testnet": {
      "environment": "testnet",
      "installed": true,
      "accountConfigured": false,
      "apiWalletConfigured": true,
      "apiWalletKeySource": "file",
      "enabled": false,
      "autoMirrorEnabled": false,
      "supportedAssets": [
        "BTC",
        "ETH",
        "SOL"
      ],
      "ready": false,
      "maximumNotionalUsd": 25,
      "mainnetSupported": false,
      "verifiedReady": false,
      "verification": {
        "id": "64a616a7-e4a6-42c3-8c20-9413e9b8e735",
        "status": "FAILED",
        "asset": "BTC",
        "requestedNotionalUsd": 12,
        "sdkVersion": "0.24.0",
        "connectivityPassed": true,
        "openFillPassed": false,
        "closeFillPassed": false,
        "restingOrderPassed": false,
        "cancelPassed": false,
        "partialFillObserved": false,
        "reconnectPassed": false,
        "reconciliationPassed": false,
        "emergencyCleanupPassed": false,
        "orphanOrderCount": 0,
        "positionMismatchCount": 0,
        "startedAt": "2026-07-18T09:16:36.124Z",
        "completedAt": "2026-07-18T09:16:36.756Z",
        "error": "Hyperliquid testnet account and dedicated API wallet are not armed",
        "failedChecks": [
          "executionArmed",
          "verificationPassed",
          "openFill",
          "closeFill",
          "restingOrder",
          "cancellation",
          "partialFill",
          "reconnect",
          "finalReconciliation",
          "emergencyCleanup",
          "accountHealthy",
          "zeroExposure",
          "noAccountMismatch",
          "reconciliationFresh"
        ]
      },
      "reconciliation": {
        "status": "not_configured",
        "lastSuccessAt": null,
        "message": null,
        "accountValue": null,
        "accountLossPct": null,
        "healthy": false,
        "orderMismatchCount": 0,
        "positionMismatchCount": 0,
        "capturedAt": null
      }
    }
  },
  "polymarket": {
    "snapshots": 137444,
    "markets": 485,
    "latestAt": "2026-07-18T12:45:58.865Z",
    "backtestRuns": 7,
    "backtestPoints": 781
  },
  "model": {
    "name": "Polymarket x Hyperliquid Signal v18",
    "selectedCandidate": "price structure 40%",
    "selectedCandidateKind": "logit-pool",
    "combinedStrategy": "no-trade guard",
    "combinedMinimumSignalZ": 0,
    "selectedFromValidation": false,
    "totalEligibleSignals": 0,
    "validationEligibleSignals": 0,
    "executionStartedAt": null,
    "executionEndedAt": null,
    "validationStartedAt": null,
    "validationEndedAt": null,
    "testStartedAt": null,
    "testEndedAt": null,
    "closestValidationCandidate": {
      "id": "signal z 0.25",
      "minimumSignalZ": 0.25,
      "signalRule": "polymarket-only",
      "minimumTrendZ": 0,
      "minimumFunding24h": 0,
      "positionPct": 0.05
    },
    "closestHoldoutAudit": {
      "strategy": {
        "id": "signal z 0.25",
        "minimumSignalZ": 0.25,
        "signalRule": "polymarket-only",
        "minimumTrendZ": 0,
        "minimumFunding24h": 0,
        "positionPct": 0.05
      },
      "trades": 0,
      "wins": 0,
      "winRate": null,
      "netReturnPct": 0,
      "benchmarkReturnPct": 0,
      "excessReturnPct": 0,
      "returnConfidenceInterval95": null,
      "statisticallyPositive": false,
      "deflatedSharpeProbability": null,
      "maxDrawdownPct": 0,
      "attribution": {
        "byAsset": [],
        "bySide": [],
        "byFundingStrength": [],
        "byConsensus": []
      }
    },
    "candidateDiagnostics": [
      {
        "strategy": {
          "id": "signal z 0.25",
          "minimumSignalZ": 0.25,
          "signalRule": "polymarket-only",
          "minimumTrendZ": 0,
          "minimumFunding24h": 0,
          "positionPct": 0.05
        },
        "validationSignals": 0,
        "trades": 0,
        "netReturnPct": 0,
        "benchmarkReturnPct": 0,
        "excessReturnPct": 0,
        "profitableFolds": 0,
        "deflatedSharpeProbability": null,
        "confidenceInterval95": null,
        "passed": false,
        "gates": [
          {
            "id": "trades",
            "label": "12取引以上",
            "passed": false
          },
          {
            "id": "significance",
            "label": "95%区間がプラス",
            "passed": false
          },
          {
            "id": "benchmark",
            "label": "単純戦略を上回る",
            "passed": false
          },
          {
            "id": "folds",
            "label": "4期間の安定性確認で3期間以上プラス",
            "passed": false
          },
          {
            "id": "selection-bias",
            "label": "試行補正後95%以上",
            "passed": false
          }
        ]
      },
      {
        "strategy": {
          "id": "signal z 0.50",
          "minimumSignalZ": 0.5,
          "signalRule": "polymarket-only",
          "minimumTrendZ": 0,
          "minimumFunding24h": 0,
          "positionPct": 0.05
        },
        "validationSignals": 0,
        "trades": 0,
        "netReturnPct": 0,
        "benchmarkReturnPct": 0,
        "excessReturnPct": 0,
        "profitableFolds": 0,
        "deflatedSharpeProbability": null,
        "confidenceInterval95": null,
        "passed": false,
        "gates": [
          {
            "id": "trades",
            "label": "12取引以上",
            "passed": false
          },
          {
            "id": "significance",
            "label": "95%区間がプラス",
            "passed": false
          },
          {
            "id": "benchmark",
            "label": "単純戦略を上回る",
            "passed": false
          },
          {
            "id": "folds",
            "label": "4期間の安定性確認で3期間以上プラス",
            "passed": false
          },
          {
            "id": "selection-bias",
            "label": "試行補正後95%以上",
            "passed": false
          }
        ]
      },
      {
        "strategy": {
          "id": "hl momentum z 0.25",
          "minimumSignalZ": 0.25,
          "signalRule": "hyperliquid-momentum",
          "minimumTrendZ": 0.1,
          "minimumFunding24h": 0,
          "positionPct": 0.05
        },
        "validationSignals": 0,
        "trades": 0,
        "netReturnPct": 0,
        "benchmarkReturnPct": 0,
        "excessReturnPct": 0,
        "profitableFolds": 0,
        "deflatedSharpeProbability": null,
        "confidenceInterval95": null,
        "passed": false,
        "gates": [
          {
            "id": "trades",
            "label": "12取引以上",
            "passed": false
          },
          {
            "id": "significance",
            "label": "95%区間がプラス",
            "passed": false
          },
          {
            "id": "benchmark",
            "label": "単純戦略を上回る",
            "passed": false
          },
          {
            "id": "folds",
            "label": "4期間の安定性確認で3期間以上プラス",
            "passed": false
          },
          {
            "id": "selection-bias",
            "label": "試行補正後95%以上",
            "passed": false
          }
        ]
      },
      {
        "strategy": {
          "id": "hl momentum z 0.50",
          "minimumSignalZ": 0.5,
          "signalRule": "hyperliquid-momentum",
          "minimumTrendZ": 0.1,
          "minimumFunding24h": 0,
          "positionPct": 0.05
        },
        "validationSignals": 0,
        "trades": 0,
        "netReturnPct": 0,
        "benchmarkReturnPct": 0,
        "excessReturnPct": 0,
        "profitableFolds": 0,
        "deflatedSharpeProbability": null,
        "confidenceInterval95": null,
        "passed": false,
        "gates": [
          {
            "id": "trades",
            "label": "12取引以上",
            "passed": false
          },
          {
            "id": "significance",
            "label": "95%区間がプラス",
            "passed": false
          },
          {
            "id": "benchmark",
            "label": "単純戦略を上回る",
            "passed": false
          },
          {
            "id": "folds",
            "label": "4期間の安定性確認で3期間以上プラス",
            "passed": false
          },
          {
            "id": "selection-bias",
            "label": "試行補正後95%以上",
            "passed": false
          }
        ]
      },
      {
        "strategy": {
          "id": "hl reversion z 0.25",
          "minimumSignalZ": 0.25,
          "signalRule": "hyperliquid-reversion",
          "minimumTrendZ": 0.1,
          "minimumFunding24h": 0,
          "positionPct": 0.05
        },
        "validationSignals": 0,
        "trades": 0,
        "netReturnPct": 0,
        "benchmarkReturnPct": 0,
        "excessReturnPct": 0,
        "profitableFolds": 0,
        "deflatedSharpeProbability": null,
        "confidenceInterval95": null,
        "passed": false,
        "gates": [
          {
            "id": "trades",
            "label": "12取引以上",
            "passed": false
          },
          {
            "id": "significance",
            "label": "95%区間がプラス",
            "passed": false
          },
          {
            "id": "benchmark",
            "label": "単純戦略を上回る",
            "passed": false
          },
          {
            "id": "folds",
            "label": "4期間の安定性確認で3期間以上プラス",
            "passed": false
          },
          {
            "id": "selection-bias",
            "label": "試行補正後95%以上",
            "passed": false
          }
        ]
      },
      {
        "strategy": {
          "id": "hl reversion z 0.50",
          "minimumSignalZ": 0.5,
          "signalRule": "hyperliquid-reversion",
          "minimumTrendZ": 0.1,
          "minimumFunding24h": 0,
          "positionPct": 0.05
        },
        "validationSignals": 0,
        "trades": 0,
        "netReturnPct": 0,
        "benchmarkReturnPct": 0,
        "excessReturnPct": 0,
        "profitableFolds": 0,
        "deflatedSharpeProbability": null,
        "confidenceInterval95": null,
        "passed": false,
        "gates": [
          {
            "id": "trades",
            "label": "12取引以上",
            "passed": false
          },
          {
            "id": "significance",
            "label": "95%区間がプラス",
            "passed": false
          },
          {
            "id": "benchmark",
            "label": "単純戦略を上回る",
            "passed": false
          },
          {
            "id": "folds",
            "label": "4期間の安定性確認で3期間以上プラス",
            "passed": false
          },
          {
            "id": "selection-bias",
            "label": "試行補正後95%以上",
            "passed": false
          }
        ]
      },
      {
        "strategy": {
          "id": "hl funding carry 0.03%",
          "minimumSignalZ": 0.25,
          "signalRule": "hyperliquid-funding-carry",
          "minimumTrendZ": 0,
          "minimumFunding24h": 0.0003,
          "positionPct": 0.05
        },
        "validationSignals": 0,
        "trades": 0,
        "netReturnPct": 0,
        "benchmarkReturnPct": 0,
        "excessReturnPct": 0,
        "profitableFolds": 0,
        "deflatedSharpeProbability": null,
        "confidenceInterval95": null,
        "passed": false,
        "gates": [
          {
            "id": "trades",
            "label": "12取引以上",
            "passed": false
          },
          {
            "id": "significance",
            "label": "95%区間がプラス",
            "passed": false
          },
          {
            "id": "benchmark",
            "label": "単純戦略を上回る",
            "passed": false
          },
          {
            "id": "folds",
            "label": "4期間の安定性確認で3期間以上プラス",
            "passed": false
          },
          {
            "id": "selection-bias",
            "label": "試行補正後95%以上",
            "passed": false
          }
        ]
      },
      {
        "strategy": {
          "id": "hl funding carry 0.06%",
          "minimumSignalZ": 0.25,
          "signalRule": "hyperliquid-funding-carry",
          "minimumTrendZ": 0,
          "minimumFunding24h": 0.0006,
          "positionPct": 0.05
        },
        "validationSignals": 0,
        "trades": 0,
        "netReturnPct": 0,
        "benchmarkReturnPct": 0,
        "excessReturnPct": 0,
        "profitableFolds": 0,
        "deflatedSharpeProbability": null,
        "confidenceInterval95": null,
        "passed": false,
        "gates": [
          {
            "id": "trades",
            "label": "12取引以上",
            "passed": false
          },
          {
            "id": "significance",
            "label": "95%区間がプラス",
            "passed": false
          },
          {
            "id": "benchmark",
            "label": "単純戦略を上回る",
            "passed": false
          },
          {
            "id": "folds",
            "label": "4期間の安定性確認で3期間以上プラス",
            "passed": false
          },
          {
            "id": "selection-bias",
            "label": "試行補正後95%以上",
            "passed": false
          }
        ]
      },
      {
        "strategy": {
          "id": "hl funding momentum 0.03%",
          "minimumSignalZ": 0.25,
          "signalRule": "hyperliquid-funding-momentum",
          "minimumTrendZ": 0,
          "minimumFunding24h": 0.0003,
          "positionPct": 0.05
        },
        "validationSignals": 0,
        "trades": 0,
        "netReturnPct": 0,
        "benchmarkReturnPct": 0,
        "excessReturnPct": 0,
        "profitableFolds": 0,
        "deflatedSharpeProbability": null,
        "confidenceInterval95": null,
        "passed": false,
        "gates": [
          {
            "id": "trades",
            "label": "12取引以上",
            "passed": false
          },
          {
            "id": "significance",
            "label": "95%区間がプラス",
            "passed": false
          },
          {
            "id": "benchmark",
            "label": "単純戦略を上回る",
            "passed": false
          },
          {
            "id": "folds",
            "label": "4期間の安定性確認で3期間以上プラス",
            "passed": false
          },
          {
            "id": "selection-bias",
            "label": "試行補正後95%以上",
            "passed": false
          }
        ]
      },
      {
        "strategy": {
          "id": "hl funding momentum 0.06%",
          "minimumSignalZ": 0.25,
          "signalRule": "hyperliquid-funding-momentum",
          "minimumTrendZ": 0,
          "minimumFunding24h": 0.0006,
          "positionPct": 0.05
        },
        "validationSignals": 0,
        "trades": 0,
        "netReturnPct": 0,
        "benchmarkReturnPct": 0,
        "excessReturnPct": 0,
        "profitableFolds": 0,
        "deflatedSharpeProbability": null,
        "confidenceInterval95": null,
        "passed": false,
        "gates": [
          {
            "id": "trades",
            "label": "12取引以上",
            "passed": false
          },
          {
            "id": "significance",
            "label": "95%区間がプラス",
            "passed": false
          },
          {
            "id": "benchmark",
            "label": "単純戦略を上回る",
            "passed": false
          },
          {
            "id": "folds",
            "label": "4期間の安定性確認で3期間以上プラス",
            "passed": false
          },
          {
            "id": "selection-bias",
            "label": "試行補正後95%以上",
            "passed": false
          }
        ]
      }
    ],
    "structuralFeatureCoverage": 1,
    "fundingFeatureCoverage": 1,
    "synchronizedExecutionCoverage": 0,
    "testSynchronizedExecutionCoverage": 0,
    "evaluationStatus": "inconclusive",
    "latestAsset": "ETH・BTC・SOL・XRP",
    "latestBrierScore": 0.03980539962244933,
    "latestAccuracy": null,
    "latestReturnPct": 0,
    "benchmarkReturnPct": 0,
    "benchmarkReturns": {
      "alwaysLongReturnPct": 0,
      "alwaysShortReturnPct": 0,
      "polymarketDirectionReturnPct": 0,
      "randomMedianReturnPct": 0,
      "randomTrials": 200,
      "bestReturnPct": 0,
      "bestLabel": "常時ロング"
    },
    "horizonStudies": [
      {
        "horizonHours": 6,
        "status": "inconclusive",
        "totalEvents": 300,
        "testEvents": 60,
        "eligibleSignals": 0,
        "trades": 0,
        "netReturnPct": 0,
        "bestBenchmarkReturnPct": 0,
        "excessReturnPct": 0,
        "deflatedSharpeProbability": null,
        "testExecutionFeatureCoverage": 1,
        "testSynchronizedExecutionCoverage": 0,
        "maximumExecutionTimingErrorMinutes": 0.000016666666666666667
      },
      {
        "horizonHours": 12,
        "status": "inconclusive",
        "totalEvents": 300,
        "testEvents": 60,
        "eligibleSignals": 0,
        "trades": 0,
        "netReturnPct": 0,
        "bestBenchmarkReturnPct": 0,
        "excessReturnPct": 0,
        "deflatedSharpeProbability": null,
        "testExecutionFeatureCoverage": 1,
        "testSynchronizedExecutionCoverage": 0,
        "maximumExecutionTimingErrorMinutes": 0.000016666666666666667
      },
      {
        "horizonHours": 24,
        "status": "inconclusive",
        "totalEvents": 300,
        "testEvents": 60,
        "eligibleSignals": 0,
        "trades": 0,
        "netReturnPct": 0,
        "bestBenchmarkReturnPct": 0,
        "excessReturnPct": 0,
        "deflatedSharpeProbability": null,
        "testExecutionFeatureCoverage": 1,
        "testSynchronizedExecutionCoverage": 0,
        "maximumExecutionTimingErrorMinutes": 0.000016666666666666667
      },
      {
        "horizonHours": 48,
        "status": "inconclusive",
        "totalEvents": 300,
        "testEvents": 60,
        "eligibleSignals": 0,
        "trades": 0,
        "netReturnPct": 0,
        "bestBenchmarkReturnPct": 0,
        "excessReturnPct": 0,
        "deflatedSharpeProbability": null,
        "testExecutionFeatureCoverage": 1,
        "testSynchronizedExecutionCoverage": 0,
        "maximumExecutionTimingErrorMinutes": 0.000016666666666666667
      }
    ],
    "excessReturnPct": 0,
    "eligibleSignals": 0,
    "testedMarkets": 660,
    "testedEvents": 0,
    "observations": 2700,
    "brierImprovement": 0.10066490862941424,
    "previousBrierScore": 0.04426092121212122,
    "confidenceInterval95": null,
    "statisticallyPositive": false,
    "deflatedSharpeProbability": null,
    "strategyTrials": 19,
    "walkForwardFolds": 0,
    "profitableValidationFolds": 0,
    "completedAt": "2026-07-18T12:42:33.026Z",
    "datasetStartedAt": "2024-03-01T00:00:00.000Z",
    "datasetEndedAt": "2026-07-17T16:00:00.000Z",
    "trades": 0,
    "longTrades": 0,
    "shortTrades": 0,
    "winRate": null,
    "averageTradeReturn": null,
    "maxDrawdownPct": 0,
    "medianObservationLagMinutes": 0.9166666666666666,
    "medianEntryLagMinutes": 0,
    "medianExitLeadMinutes": 0.000016666666666666667,
    "maximumExecutionTimingErrorMinutes": 0.000016666666666666667,
    "probabilityLadderEvents": 240,
    "probabilityLadderViolationEvents": 0,
    "aiPredictions": 268,
    "aiResolved": 0,
    "aiBrierScore": null,
    "marketBrierScore": null,
    "aiImprovement": null,
    "paperRuns": 6,
    "runningPaperRuns": 0,
    "paperSnapshots": 1075,
    "paperOrders": 7,
    "paperFills": 7,
    "paperReturnPct": 0
  },
  "paperExperiment": {
    "label": "Polymarket単体の仮想売買",
    "strategy": null,
    "status": "not_running",
    "realMoney": false,
    "initialCash": null,
    "equity": null,
    "returnPct": null,
    "unrealizedPnl": null,
    "openPositions": 0,
    "fills": 0,
    "updatedAt": null
  },
  "backtestQuality": {
    "status": "inconclusive",
    "checks": [
      {
        "label": "過去データだけで取引ルールを再選択する4期間検証",
        "passed": false
      },
      {
        "label": "全市場を決着24時間前で統一",
        "passed": true
      },
      {
        "label": "未使用期間の同期板価格で売買検証",
        "passed": false
      },
      {
        "label": "最終テストの売買価格を90%以上取得",
        "passed": true
      },
      {
        "label": "最終テストの1分同期板価格を90%以上取得",
        "passed": false
      },
      {
        "label": "売買時刻の誤差を5分以内に制限",
        "passed": true
      },
      {
        "label": "価格帯の確率矛盾を単調補正",
        "passed": true
      },
      {
        "label": "同期板・手数料・滑り・実期間の資金調達を反映",
        "passed": false
      },
      {
        "label": "最終テストの資金調達率を90%以上取得",
        "passed": true
      },
      {
        "label": "売買可能な最終テスト15イベント以上",
        "passed": false
      },
      {
        "label": "最終テスト12取引以上",
        "passed": false
      },
      {
        "label": "採用戦略が最終テストで単純戦略を上回る",
        "passed": false
      },
      {
        "label": "最有力候補が未使用期間でプラスかつ単純戦略を上回る",
        "passed": false
      },
      {
        "label": "ブロック再標本化95%区間がプラス",
        "passed": false
      },
      {
        "label": "試行回数補正後も95%以上",
        "passed": false
      }
    ]
  },
  "hyperliquid": {
    "snapshots": 8285,
    "latestAt": "2026-07-18T12:45:55.484Z",
    "assets": [
      {
        "asset": "BTC",
        "price": 64170.5,
        "change24hPct": 0.016707332530578656,
        "dayVolume": 1250187309.29759,
        "openInterestUsd": 2500603460.0639997,
        "fundingRate": 0.0000125,
        "capturedAt": "2026-07-18T12:45:55.484Z"
      },
      {
        "asset": "ETH",
        "price": 1844.85,
        "change24hPct": 0.008610792192881744,
        "dayVolume": 476310370.6267801,
        "openInterestUsd": 1774512274.2928002,
        "fundingRate": 0.0000125,
        "capturedAt": "2026-07-18T12:45:55.484Z"
      },
      {
        "asset": "SOL",
        "price": 74.9695,
        "change24hPct": 0.007451454679835878,
        "dayVolume": 81040841.51226999,
        "openInterestUsd": 328910156.0577601,
        "fundingRate": -0.0000044701,
        "capturedAt": "2026-07-18T12:45:55.484Z"
      },
      {
        "asset": "XRP",
        "price": 1.08915,
        "change24hPct": 0.008659010927949629,
        "dayVolume": 17116389.6358,
        "openInterestUsd": 101945908.2982,
        "fundingRate": 0.0000125,
        "capturedAt": "2026-07-18T12:45:55.484Z"
      },
      {
        "asset": "HYPE",
        "price": 58.7735,
        "change24hPct": -0.020360030002500196,
        "dayVolume": 258315162.79204,
        "openInterestUsd": 1333837127.4500005,
        "fundingRate": 0.0000125,
        "capturedAt": "2026-07-18T12:45:55.484Z"
      }
    ]
  },
  "operations": {
    "alerts": {
      "status": "healthy",
      "message": "異常1件を監視中",
      "lastSuccessAt": "2026-07-18T12:46:09.554Z",
      "webhookConfigured": false
    },
    "tunnel": {
      "mode": "quick",
      "status": "healthy",
      "publicUrl": "https://tent-asking-mining-album.trycloudflare.com",
      "fixedUrl": false,
      "fallback": false,
      "publishedAt": "2026-07-18T12:43:49.269Z",
      "lastCheckedAt": "2026-07-18T12:46:06.735Z",
      "consecutiveFailures": 0,
      "updatedAt": "2026-07-18T12:46:06.735Z"
    },
    "backup": {
      "encrypted": true,
      "copies": 14,
      "latestAt": "2026-07-18T12:45:55.025Z",
      "verifiedAt": "2026-07-18T12:45:55.602Z",
      "status": "healthy",
      "message": "暗号化・復号・SQLite整合性を確認済みです"
    }
  },
  "pipelines": [
    {
      "id": "polymarket",
      "label": "価格同期収集",
      "cadence": "1分ごと",
      "status": "healthy",
      "lastSuccessAt": "2026-07-18T12:45:58.934Z",
      "records": 130795
    },
    {
      "id": "hyperliquid",
      "label": "相場データ収集",
      "cadence": "1分ごと",
      "status": "healthy",
      "lastSuccessAt": "2026-07-18T12:45:55.491Z",
      "records": 8285
    },
    {
      "id": "realtime-market-data",
      "label": "秒単位の板収集",
      "cadence": "5秒ごと",
      "status": "healthy",
      "lastSuccessAt": "2026-07-18T12:46:30.956Z",
      "records": 50184
    },
    {
      "id": "backtest",
      "label": "モデル再検証",
      "cadence": "6時間ごと",
      "status": "healthy",
      "lastSuccessAt": "2026-07-18T12:42:33.033Z",
      "records": 4488
    },
    {
      "id": "short-term-backtest",
      "label": "15分モデル過去検証",
      "cadence": "6時間ごと",
      "status": "healthy",
      "lastSuccessAt": "2026-07-18T12:45:54.722Z",
      "records": 25234
    },
    {
      "id": "realtime-short-term-backtest",
      "label": "5秒板リプレイ",
      "cadence": "30分ごと",
      "status": "healthy",
      "lastSuccessAt": "2026-07-18T12:45:54.723Z",
      "records": 351
    },
    {
      "id": "forward-experiment",
      "label": "固定フォワード検証",
      "cadence": "5分ごと",
      "status": "healthy",
      "lastSuccessAt": "2026-07-18T12:45:59.455Z",
      "records": 2346
    },
    {
      "id": "short-term-direction",
      "label": "15分モデル検証",
      "cadence": "1分ごと",
      "status": "healthy",
      "lastSuccessAt": "2026-07-18T12:46:12.016Z",
      "records": 12523
    }
  ]
}
